{
  "project_info": {
    "project_number": "159521160544",
    "project_id": "farkha-c7248",
    "storage_bucket": "farkha-c7248.firebasestorage.app"
  },
  "client": [
    {
      "client_info": {
        "mobilesdk_app_id": "1:159521160544:android:8bb038def7e3670a21f205",
        "android_client_info": {
          "package_name": "ni.nims.frkha"
        }
      },
      "oauth_client": [
        {
          "client_id": "159521160544-4ali0c0agd6b7logi18oust6td1g877c.apps.googleusercontent.com",
          "client_type": 1,
          "android_info": {
            "package_name": "ni.nims.frkha",
            "certificate_hash": "c262386f0936ee95598be9c881f965b1bac0288d"
          }
        },
        {
          "client_id": "159521160544-ac9jmah04pfebol1ltpqqbsa6jtgr5qo.apps.googleusercontent.com",
          "client_type": 1,
          "android_info": {
            "package_name": "ni.nims.frkha",
            "certificate_hash": "d27637b4446ceedfc1beed0079e43eb86a2658d4"
          }
        },
        {
          "client_id": "159521160544-v3257v1f5nb0jqq4ijsiaj30qmn8lno4.apps.googleusercontent.com",
          "client_type": 1,
          "android_info": {
            "package_name": "ni.nims.frkha",
            "certificate_hash": "0fade86af52997e5dde562ded1cb2e303f188d6c"
          }
        },
        {
          "client_id": "159521160544-a50bd58sqojqi4gu07ejinjab17asct9.apps.googleusercontent.com",
          "client_type": 3
        }
      ],
      "api_key": [
        {
          "current_key": "AIzaSyAkcXEc6ICXvD0W4GMHZ9JDZfURYJSUWLQ"
        }
      ],
      "services": {
        "appinvite_service": {
          "other_platform_oauth_client": [
            {
              "client_id": "159521160544-a50bd58sqojqi4gu07ejinjab17asct9.apps.googleusercontent.com",
              "client_type": 3
            },
            {
              "client_id": "159521160544-nrvehq83c0ne2fsd6lvrj2502dqrrpte.apps.googleusercontent.com",
              "client_type": 2,
              "ios_info": {
                "bundle_id": "com.example.farkhaApp"
              }
            }
          ]
        }
      },
      "admob_app_id": "ca-app-pub-8595701567488603~3243480822"
    }
  ],
  "configuration_version": "1"
}